{
  "name": "live2d-haxe",
  "url": "https://github.com/Dingdang255/live2d-haxe",
  "license": "MIT",
  "tags": ["live2d", "cubism", "openfl", "flixel", "heaps", "cpp", "hl", "native", "multi-backend"],
  "description": "Live2D Cubism SDK for Haxe - GPU shader rendering with multi-backend abstraction (cpp + hl, OpenFL/Flixel/Heaps)",
  "version": "1.1.0",
  "classPath": "src",
  "main": "live2d.CLI",
  "releasenote": "v1.1.0: New features: cross-backend perf panel (L2DPerfPanel + 3 implementations), VTube Studio model adapter (L2DVTuberModel with subdir scanning), runtime physics tuner (L2DPhysicsTuner with gravity/wind/strength control), mask RT 2x SSAA, demo polish (dynamic statusText Y). No breaking changes.",
  "contributors": ["Dingdang255"],
  "dependencies": {
    "hxcpp": "4.2.1"
  }
}
